dyslexml/__init__.py
dyslexml/todict.py
dyslexml/toobject.py
dyslexml/toxml.py
dyslexml-1.2.dist-info/DESCRIPTION.rst
dyslexml-1.2.dist-info/METADATA
dyslexml-1.2.dist-info/RECORD
dyslexml-1.2.dist-info/WHEEL
dyslexml-1.2.dist-info/metadata.json
dyslexml-1.2.dist-info/top_level.txt
