Metadata-Version: 2.0
Name: dyslexml
Version: 1.2
Summary: Dyslexml is for those who hate working with XML and wish there was a better way.
Home-page: https://github.com/ccubed/Dyslexml
Author: Charles Click
Author-email: ccubed.techno@gmail.com
License: MIT
Keywords: XML Converters
Platform: UNKNOWN
Classifier: Intended Audience :: Developers
Classifier: License :: OSI Approved :: MIT License
Classifier: Programming Language :: Python :: 3
Classifier: Topic :: Software Development :: Libraries
